calingen/__init__.py
calingen/admin.py
calingen/apps.py
calingen/checks.py
calingen/constants.py
calingen/exceptions.py
calingen/settings.py
calingen/urls.py
calingen/contrib/__init__.py
calingen/contrib/compilers/__init__.py
calingen/contrib/compilers/copy_paste/__init__.py
calingen/contrib/compilers/copy_paste/compiler.py
calingen/contrib/compilers/download/__init__.py
calingen/contrib/compilers/download/compiler.py
calingen/contrib/compilers/html_or_download/__init__.py
calingen/contrib/compilers/html_or_download/compiler.py
calingen/contrib/layouts/__init__.py
calingen/contrib/layouts/lineatur/__init__.py
calingen/contrib/layouts/lineatur/apps.py
calingen/contrib/layouts/lineatur/lineatur.py
calingen/contrib/layouts/lineatur/static/lineatur/lineatur_base.css
calingen/contrib/layouts/lineatur/templates/lineatur/config_form.html
calingen/contrib/layouts/lineatur/templates/lineatur/form_field_group.html
calingen/contrib/layouts/lineatur/templates/lineatur/layout.html
calingen/contrib/layouts/simple_event_list/__init__.py
calingen/contrib/layouts/simple_event_list/apps.py
calingen/contrib/layouts/simple_event_list/simple_event_list.py
calingen/contrib/layouts/simple_event_list/templates/simple_event_list/tex/base.tex
calingen/contrib/layouts/simple_event_list/templates/simple_event_list/tex/simple_event_list.tex
calingen/contrib/layouts/simple_event_list/templates/simple_event_list/tex/single_entry_line.tex
calingen/contrib/layouts/year_by_week/__init__.py
calingen/contrib/layouts/year_by_week/apps.py
calingen/contrib/layouts/year_by_week/year_by_week.py
calingen/contrib/layouts/year_by_week/templates/year_by_week/tex/base.tex
calingen/contrib/layouts/year_by_week/templates/year_by_week/tex/year_by_week.tex
calingen/contrib/providers/__init__.py
calingen/contrib/providers/german_holidays/__init__.py
calingen/contrib/providers/german_holidays/apps.py
calingen/contrib/providers/german_holidays/provider.py
calingen/forms/__init__.py
calingen/forms/fields.py
django_calingen-1.1.1.dist-info/LICENSE
django_calingen-1.1.1.dist-info/WHEEL
django_calingen-1.1.1.dist-info/METADATA
django_calingen-1.1.1.dist-info/RECORD
