Metadata-Version: 2.1
Name: django-calingen
Version: 1.1.1
Summary: A pluggable Django application to generate analogous, legacy, paper-based calendar inlays.
Author: Mischback
Requires-Python: >=3.7
Classifier: Development Status :: 5 - Production/Stable
Classifier: Framework :: Django :: 3.1
Classifier: Framework :: Django :: 3.2
Classifier: Framework :: Django :: 4.0
Classifier: Framework :: Django :: 4.1
Classifier: Intended Audience :: End Users/Desktop
Classifier: License :: OSI Approved :: MIT License
Classifier: Programming Language :: Python :: 3 :: Only
Classifier: Programming Language :: Python :: 3.7
Classifier: Programming Language :: Python :: 3.8
Classifier: Programming Language :: Python :: 3.9
Classifier: Programming Language :: Python :: 3.10
Classifier: Topic :: Office/Business :: Scheduling
Classifier: Topic :: Printing
Classifier: Topic :: Text Processing :: Markup :: HTML
Classifier: Topic :: Text Processing :: Markup :: LaTeX
Requires-Dist: Django >=3.1
Requires-Dist: python-dateutil >=2.8
Project-URL: Source, https://github.com/Mischback/django-calingen
